python_nbaclient/__init__.py
python_nbaclient/constants.py
python_nbaclient/teams.py
python_nbaclient/utils.py
python_nbaclient-0.0.7.dist-info/LICENSE
python_nbaclient-0.0.7.dist-info/METADATA
python_nbaclient-0.0.7.dist-info/WHEEL
python_nbaclient-0.0.7.dist-info/top_level.txt
python_nbaclient-0.0.7.dist-info/RECORD
