Metadata-Version: 2.1
Name: python-nbaclient
Version: 0.0.7
Summary: A Python Wrapper of NBA RESTful Stats APIs
Home-page: https://github.com/xuhang57/python_nbaclient
Author: Lucas H. Xu
Author-email: lucasxu.pub@gmail.com
License: GPLv3
Keywords: nba python client api
Platform: UNKNOWN
Classifier: Programming Language :: Python :: 3
Classifier: Programming Language :: Python :: 3.8
Classifier: License :: OSI Approved :: GNU General Public License v3 (GPLv3)
Classifier: Operating System :: OS Independent
Requires-Python: >=3.8
Requires-Dist: requests
Requires-Dist: pprint
